mad.cpython-38-i386-linux-gnu.so
pylibmad.libs/libmad-3803e77f.so.0.2.1
pylibmad-0.2.dist-info/top_level.txt
pylibmad-0.2.dist-info/WHEEL
pylibmad-0.2.dist-info/METADATA
pylibmad-0.2.dist-info/AUTHORS
pylibmad-0.2.dist-info/RECORD
pylibmad-0.2.dist-info/COPYING
